pandas_streaming/__init__.py
pandas_streaming/ext_test_case.py
pandas_streaming/data/__init__.py
pandas_streaming/data/dummy.py
pandas_streaming/df/__init__.py
pandas_streaming/df/connex_split.py
pandas_streaming/df/dataframe.py
pandas_streaming/df/dataframe_helpers.py
pandas_streaming/df/dataframe_io.py
pandas_streaming/df/dataframe_io_helpers.py
pandas_streaming/df/dataframe_split.py
pandas_streaming/exc/__init__.py
pandas_streaming/exc/exc_streaming.py
pandas_streaming-0.5.1.dist-info/LICENSE.txt
pandas_streaming-0.5.1.dist-info/METADATA
pandas_streaming-0.5.1.dist-info/WHEEL
pandas_streaming-0.5.1.dist-info/top_level.txt
pandas_streaming-0.5.1.dist-info/RECORD
